yanivtils/__init__.py
yanivtils/yanivtils.py
yanivtils-0.2.2.dist-info/METADATA
yanivtils-0.2.2.dist-info/WHEEL
yanivtils-0.2.2.dist-info/top_level.txt
yanivtils-0.2.2.dist-info/RECORD
