Metadata-Version: 2.1
Name: yanivtils
Version: 0.2.2
Summary: A collection of useful utilities for Python developers
Author: Yaniv
Author-email: yanivdorgalron@gmail.com
Classifier: Programming Language :: Python :: 3
Classifier: License :: OSI Approved :: MIT License
Classifier: Operating System :: OS Independent
Requires-Python: >=3.6
Requires-Dist: GPUtil
